fma_django/__init__.py
fma_django/admin.py
fma_django/apps.py
fma_django/authenticators.py
fma_django/models.py
fma_django/version.py
fma_django/migrations/0001_initial.py
fma_django/migrations/__init__.py
fma_django_api/__init__.py
fma_django_api/apps.py
fma_django_api/urls.py
fma_django_api/utils.py
fma_django_api/v1/__init__.py
fma_django_api/v1/fields.py
fma_django_api/v1/filters.py
fma_django_api/v1/paginators.py
fma_django_api/v1/permissions.py
fma_django_api/v1/serializers.py
fma_django_api/v1/urls.py
fma_django_api/v1/views.py
fma_django_connectors/__init__.py
fma_django_connectors/aggregator_connector.py
fma_django_connectors/api_handlers.py
fma_django_connectors/metadata_connector.py
fma_django_connectors/utils.py
fma_django-0.0.1.dist-info/LICENSE
fma_django-0.0.1.dist-info/METADATA
fma_django-0.0.1.dist-info/WHEEL
fma_django-0.0.1.dist-info/top_level.txt
fma_django-0.0.1.dist-info/RECORD
