Metadata-Version: 2.1
Name: fma-django
Version: 0.0.1
Summary: Federated Model Aggregation's Django Connectors
Home-page: https://github.com/capitalone/federated-model-aggregation
Author: Kenny Bean, Tyler Farnan, Taylor Turner, Michael Davis, Jeremy Goodsitt
License: Apache License, Version 2.0
Keywords: Federated Learning
Classifier: Development Status :: 5 - Production/Stable
Classifier: Intended Audience :: Developers
Classifier: Intended Audience :: Information Technology
Classifier: Intended Audience :: Education
Classifier: Intended Audience :: Science/Research
Classifier: Topic :: Education
Classifier: Topic :: Scientific/Engineering :: Information Analysis
Classifier: License :: OSI Approved :: Apache Software License
Classifier: Topic :: Scientific/Engineering
Classifier: Programming Language :: Python :: 3
Requires-Python: >=3.8
License-File: LICENSE
Requires-Dist: Django (==4.1.3)
Requires-Dist: django-q (==1.3.9)
Requires-Dist: django-mptt (==0.13.4)
Requires-Dist: numpy (==1.22.2)
Requires-Dist: jsonschema (==4.4.0)
Requires-Dist: django-storages (==1.12.3)
Requires-Dist: boto3 (==1.26.11)
Requires-Dist: psycopg2-binary (==2.9.3)
Provides-Extra: api
Requires-Dist: djangorestframework (==3.13.1) ; extra == 'api'
Requires-Dist: jsonschema (==4.4.0) ; extra == 'api'
Requires-Dist: django-filter (==22.1) ; extra == 'api'
Requires-Dist: apig-wsgi (==2.15.0) ; extra == 'api'
